pydantic_view/__init__.py
pydantic_view/pydantic_view.py
pydantic_view-2.0.1.dist-info/LICENSE
pydantic_view-2.0.1.dist-info/METADATA
pydantic_view-2.0.1.dist-info/WHEEL
pydantic_view-2.0.1.dist-info/RECORD
